{"type": "Feature", "id": 13630, "properties": {"woe:id": 13630, "woe:parent_id": 26042, "woe:name": "Bramley", "woe:placetype": 22, "woe:placetype_name": "Suburb", "woe:lang": "ENG", "iso:country": "GB", "meta:provider": ["geoplanet:7.3.1", "geoplanet:7.3.2", "geoplanet:7.4.0", "geoplanet:7.4.1", "geoplanet:7.5.1", "geoplanet:7.5.2", "geoplanet:7.6.0", "geoplanet:7.8.1", "geoplanet:7.9.0", "geoplanet:7.10.0", "geoplanet:8.0.0", "woeplanet:8.0.0"], "meta:indexed": "2020-08-20T19:45:29.804685", "meta:updated": "2020-09-19T16:04:18.200834", "woe:adjacent": [33471, 27890, 20094278, 39763, 35922, 25430, 14956, 43825, 11043], "woe:hierarchy": {"continent": 24865675, "country": 23424975, "town": 0, "planet": 1, "county": 12602197, "suburb": 0, "state": 24554868, "region": 0, "localadmin": 12695873}, "woe:timezone_id": 28350903, "woe:concordances": {"gn:id": 2654921, "qs:id": 1082048}, "woe:hash": "gcwf4g459ndx", "geom:min_latitude": 53.806179, "woe:centroid": [-1.63417, 53.806179], "geom:latitude": 53.806179, "woe:max_longitude": -1.63417, "geom:max_longitude": -1.63417, "geom:centroid": [-1.63417, 53.806179], "geom:max_latitude": 53.806179, "woe:min_latitude": 53.806179, "woe:min_longitude": -1.63417, "geom:longitude": -1.63417, "geom:hash": "gcwf4g459ndx", "woe:latitude": 53.806179, "geom:min_longitude": -1.63417, "woe:longitude": -1.63417, "woe:max_latitude": 53.806179, "woe:children": {"poi": [56495199, 56428905, 56429055, 56429062, 56429427, 56429872, 56430398, 56431786, 56432364, 56433793]}, "woe:repo": "woeplanet-suburb-gb"}, "geometry": {"coordinates": [-1.63417, 53.806179], "type": "Point"}}